{
  "title": "Volition",
  "libraries": [
    "GameServices",
    "BaseECSGame",
    "GameState",
    "SeededRandom",
    "ComponentGenerator",
    "SceneManager",
    "BaseLoader",
    "VolitionGame"
  ],
  "systems": [
    "LayoutSystem",
    "VolitionGameSystem",
    "DeckSystem",
    "CardFlowSystem",
    "HandSystem",
    "TableauSystem",
    "FoundationSystem",
    "InputSystem",
    "RenderSystem",
    "TutorialSystem"
  ],
  "interface": "main",
  "appLibrary": "VolitionGame",
  "appLoaderLibrary": "BaseLoader",
  "initialScene": "game",
  "maxEntities": 1024,
  "handCapacity": 5,
  "tableauColumns": 6,
  "animationSpeed": 4000
}
