{
  "id": "vitality",
  "type": "suffix",
  "tierNames": [
    "of the Boar",
    "of the Elk",
    "of the Whale",
    "of the Mountain"
  ],
  "applicable": [
    "armor",
    "jewelry"
  ],
  "tiers": [
    {
      "ilvl": 1,
      "min": 2,
      "max": 4
    },
    {
      "ilvl": 6,
      "min": 4,
      "max": 7
    },
    {
      "ilvl": 12,
      "min": 7,
      "max": 11
    },
    {
      "ilvl": 18,
      "min": 11,
      "max": 16
    }
  ],
  "stat": "vitality",
  "damageTags": null,
  "text": "+{v} to Vitality",
  "fileName": "vitality"
}