{"title": "WFC Piece: rock/pit", "published": false, "isWfcPiece": true, "wfc": {"set": "rock", "weight": 1, "edges": {"n": "w", "e": "w", "s": "w", "w": "w"}, "features": ["chest"]}, "tiles": [[4, 4, 4, 4, 4, 4, 4, 4], [4, 4, 4, 4, 4, 4, 4, 4], [4, 4, 2, 2, 2, 2, 4, 4], [4, 4, 2, 2, 2, 2, 4, 4], [4, 4, 2, 2, 2, 2, 4, 4], [4, 4, 2, 2, 2, 2, 4, 4], [4, 4, 4, 4, 4, 4, 4, 4], [4, 4, 4, 4, 4, 4, 4, 4]], "heights": [[2, 2, 2, 2, 2, 2, 2, 2], [2, 2, 2, 2, 2, 2, 2, 2], [2, 2, 2, 2, 2, 2, 2, 2], [2, 2, 2, 2, 2, 2, 2, 2], [2, 2, 2, 2, 2, 2, 2, 2], [2, 2, 2, 2, 2, 2, 2, 2], [2, 2, 2, 2, 2, 2, 2, 2], [2, 2, 2, 2, 2, 2, 2, 2]], "entities": [{"type": "treasure_chest", "tx": 3.5, "tz": 3.5}, {"type": "goldVein", "tx": 5, "tz": 2.5}], "fileName": "piece_rock_pit"}